AlgoPlus/__init__.py
AlgoPlus/CTP/ApiConst.py
AlgoPlus/CTP/ApiStruct.py
AlgoPlus/CTP/AuthenticateHelper.py
AlgoPlus/CTP/FutureAccount.py
AlgoPlus/CTP/MdApi.py
AlgoPlus/CTP/MdApiBase.cp310-win_amd64.pyd
AlgoPlus/CTP/QueryInstrumentHelper.py
AlgoPlus/CTP/RiskManager.py
AlgoPlus/CTP/TraderApiBase.cp310-win_amd64.pyd
AlgoPlus/CTP/__init__.py
AlgoPlus/CTP/thostmduserapi_se.dll
AlgoPlus/CTP/thosttraderapi_se.dll
AlgoPlus/ta/__init__.py
AlgoPlus/ta/time_bar.py
AlgoPlus/utils/__init__.py
AlgoPlus/utils/base_field.py
AlgoPlus-3.1.dist-info/METADATA
AlgoPlus-3.1.dist-info/WHEEL
AlgoPlus-3.1.dist-info/top_level.txt
AlgoPlus-3.1.dist-info/RECORD
