Metadata-Version: 2.1
Name: AlgoPlus
Version: 3.1
Summary: AlgoPlus
Home-page: http://algo.plus
Author: algo.plus
Author-email: algo@algo.com
License: MIT
Keywords: CTP 量化交易 算法交易 程序化交易
Platform: Windows
Platform: Linux
